{
  "terms": {
    "url": "https://www.bankofcanada.ca/terms/"
  },
  "seriesDetail": {
    "CPI_COMMON": {
      "label": "CPI-common",
      "description": "CPI-common",
      "dimension": {
        "key": "d",
        "name": "Date"
      }
    },
    "CPI_MEDIAN": {
      "label": "CPI-median",
      "description": "CPI-median",
      "dimension": {
        "key": "d",
        "name": "Date"
      }
    },
    "CPI_TRIM": {
      "label": "CPI-trim",
      "description": "CPI-trim",
      "dimension": {
        "key": "d",
        "name": "Date"
      }
    },
    "V37151": {
      "label": "M1+ (gross) (Seasonally adjusted)",
      "description": "",
      "dimension": {
        "key": "d",
        "name": "Date"
      }
    },
    "V37152": {
      "label": "M1++ (gross) (Seasonally adjusted)",
      "description": "",
      "dimension": {
        "key": "d",
        "name": "Date"
      }
    },
    "V41552801": {
      "label": "M2++ (gross) (Seasonally adjusted)",
      "description": "M2++ (gross)",
      "dimension": {
        "key": "d",
        "name": "Date"
      }
    },
    "V41690973": {
      "label": "Total CPI",
      "description": "Total CPI",
      "dimension": {
        "key": "d",
        "name": "Date"
      }
    }
  },
  "observations": [
    {
      "d": "2026-01-01",
      "V41690973": {
        "v": "165.0"
      },
      "CPI_COMMON": {
        "v": "2.7"
      },
      "CPI_MEDIAN": {
        "v": "2.5"
      },
      "CPI_TRIM": {
        "v": "2.4"
      }
    },
    {
      "d": "2025-12-01",
      "V41690973": {
        "v": "165.0"
      },
      "CPI_COMMON": {
        "v": "2.8"
      },
      "CPI_MEDIAN": {
        "v": "2.6"
      },
      "CPI_TRIM": {
        "v": "2.7"
      },
      "V37151": {
        "v": "1733846"
      },
      "V37152": {
        "v": "2323102"
      },
      "V41552801": {
        "v": "5193591"
      }
    },
    {
      "d": "2025-11-01",
      "V41690973": {
        "v": "165.4"
      },
      "CPI_COMMON": {
        "v": "2.8"
      },
      "CPI_MEDIAN": {
        "v": "2.8"
      },
      "CPI_TRIM": {
        "v": "2.9"
      },
      "V37151": {
        "v": "1742935"
      },
      "V37152": {
        "v": "2331451"
      },
      "V41552801": {
        "v": "5109388"
      }
    },
    {
      "d": "2025-10-01",
      "V41690973": {
        "v": "165.3"
      },
      "CPI_COMMON": {
        "v": "2.7"
      },
      "CPI_MEDIAN": {
        "v": "2.9"
      },
      "CPI_TRIM": {
        "v": "3.0"
      },
      "V37151": {
        "v": "1731782"
      },
      "V37152": {
        "v": "2312335"
      },
      "V41552801": {
        "v": "5089951"
      }
    },
    {
      "d": "2025-09-01",
      "V41690973": {
        "v": "164.9"
      },
      "CPI_COMMON": {
        "v": "2.7"
      },
      "CPI_MEDIAN": {
        "v": "3.1"
      },
      "CPI_TRIM": {
        "v": "3.1"
      },
      "V37151": {
        "v": "1710482"
      },
      "V37152": {
        "v": "2279909"
      },
      "V41552801": {
        "v": "5040078"
      }
    },
    {
      "d": "2025-08-01",
      "V41690973": {
        "v": "164.8"
      },
      "CPI_COMMON": {
        "v": "2.6"
      },
      "CPI_MEDIAN": {
        "v": "3.0"
      },
      "CPI_TRIM": {
        "v": "3.0"
      },
      "V37151": {
        "v": "1706938"
      },
      "V37152": {
        "v": "2277682"
      },
      "V41552801": {
        "v": "5026422"
      }
    },
    {
      "d": "2025-07-01",
      "V41690973": {
        "v": "164.9"
      },
      "CPI_COMMON": {
        "v": "2.6"
      },
      "CPI_MEDIAN": {
        "v": "3.0"
      },
      "CPI_TRIM": {
        "v": "3.1"
      },
      "V37151": {
        "v": "1687764"
      },
      "V37152": {
        "v": "2257789"
      },
      "V41552801": {
        "v": "5000162"
      }
    },
    {
      "d": "2025-06-01",
      "V41690973": {
        "v": "164.4"
      },
      "CPI_COMMON": {
        "v": "2.6"
      },
      "CPI_MEDIAN": {
        "v": "2.9"
      },
      "CPI_TRIM": {
        "v": "3.1"
      },
      "V37151": {
        "v": "1679430"
      },
      "V37152": {
        "v": "2255709"
      },
      "V41552801": {
        "v": "4993022"
      }
    },
    {
      "d": "2025-05-01",
      "V41690973": {
        "v": "164.3"
      },
      "CPI_COMMON": {
        "v": "2.6"
      },
      "CPI_MEDIAN": {
        "v": "2.9"
      },
      "CPI_TRIM": {
        "v": "3.0"
      },
      "V37151": {
        "v": "1664914"
      },
      "V37152": {
        "v": "2236587"
      },
      "V41552801": {
        "v": "4974729"
      }
    },
    {
      "d": "2025-04-01",
      "V41690973": {
        "v": "163.4"
      },
      "CPI_COMMON": {
        "v": "2.5"
      },
      "CPI_MEDIAN": {
        "v": "3.1"
      },
      "CPI_TRIM": {
        "v": "3.1"
      },
      "V37151": {
        "v": "1649929"
      },
      "V37152": {
        "v": "2213993"
      },
      "V41552801": {
        "v": "4951692"
      }
    },
    {
      "d": "2025-03-01",
      "V41690973": {
        "v": "163.5"
      },
      "CPI_COMMON": {
        "v": "2.4"
      },
      "CPI_MEDIAN": {
        "v": "2.7"
      },
      "CPI_TRIM": {
        "v": "2.9"
      },
      "V37151": {
        "v": "1645611"
      },
      "V37152": {
        "v": "2204333"
      },
      "V41552801": {
        "v": "4937288"
      }
    },
    {
      "d": "2025-02-01",
      "V41690973": {
        "v": "163.0"
      },
      "CPI_COMMON": {
        "v": "2.5"
      },
      "CPI_MEDIAN": {
        "v": "2.7"
      },
      "CPI_TRIM": {
        "v": "2.9"
      },
      "V37151": {
        "v": "1640275"
      },
      "V37152": {
        "v": "2192131"
      },
      "V41552801": {
        "v": "4928278"
      }
    },
    {
      "d": "2025-01-01",
      "V41690973": {
        "v": "161.3"
      },
      "CPI_COMMON": {
        "v": "2.2"
      },
      "CPI_MEDIAN": {
        "v": "2.5"
      },
      "CPI_TRIM": {
        "v": "2.8"
      },
      "V37151": {
        "v": "1634436"
      },
      "V37152": {
        "v": "2177112"
      },
      "V41552801": {
        "v": "4908785"
      }
    },
    {
      "d": "2024-12-01",
      "V41690973": {
        "v": "161.2"
      },
      "CPI_COMMON": {
        "v": "2.0"
      },
      "CPI_MEDIAN": {
        "v": "2.4"
      },
      "CPI_TRIM": {
        "v": "2.5"
      },
      "V37151": {
        "v": "1612783"
      },
      "V37152": {
        "v": "2144760"
      },
      "V41552801": {
        "v": "4888652"
      }
    },
    {
      "d": "2024-11-01",
      "V41690973": {
        "v": "161.8"
      },
      "CPI_COMMON": {
        "v": "2.0"
      },
      "CPI_MEDIAN": {
        "v": "2.6"
      },
      "CPI_TRIM": {
        "v": "2.7"
      },
      "V37151": {
        "v": "1595602"
      },
      "V37152": {
        "v": "2124378"
      },
      "V41552801": {
        "v": "4823461"
      }
    },
    {
      "d": "2024-10-01",
      "V41690973": {
        "v": "161.8"
      },
      "CPI_COMMON": {
        "v": "2.2"
      },
      "CPI_MEDIAN": {
        "v": "2.7"
      },
      "CPI_TRIM": {
        "v": "2.8"
      },
      "V37151": {
        "v": "1571481"
      },
      "V37152": {
        "v": "2091823"
      },
      "V41552801": {
        "v": "4804153"
      }
    },
    {
      "d": "2024-09-01",
      "V41690973": {
        "v": "161.1"
      },
      "CPI_COMMON": {
        "v": "2.1"
      },
      "CPI_MEDIAN": {
        "v": "2.5"
      },
      "CPI_TRIM": {
        "v": "2.6"
      },
      "V37151": {
        "v": "1537077"
      },
      "V37152": {
        "v": "2051513"
      },
      "V41552801": {
        "v": "4758384"
      }
    },
    {
      "d": "2024-08-01",
      "V41690973": {
        "v": "161.8"
      },
      "CPI_COMMON": {
        "v": "1.9"
      },
      "CPI_MEDIAN": {
        "v": "2.6"
      },
      "CPI_TRIM": {
        "v": "2.6"
      },
      "V37151": {
        "v": "1530003"
      },
      "V37152": {
        "v": "2045439"
      },
      "V41552801": {
        "v": "4740016"
      }
    },
    {
      "d": "2024-07-01",
      "V41690973": {
        "v": "162.1"
      },
      "CPI_COMMON": {
        "v": "2.2"
      },
      "CPI_MEDIAN": {
        "v": "2.8"
      },
      "CPI_TRIM": {
        "v": "2.8"
      },
      "V37151": {
        "v": "1527537"
      },
      "V37152": {
        "v": "2042336"
      },
      "V41552801": {
        "v": "4725725"
      }
    },
    {
      "d": "2024-06-01",
      "V41690973": {
        "v": "161.4"
      },
      "CPI_COMMON": {
        "v": "2.2"
      },
      "CPI_MEDIAN": {
        "v": "3.1"
      },
      "CPI_TRIM": {
        "v": "3.0"
      },
      "V37151": {
        "v": "1520474"
      },
      "V37152": {
        "v": "2040159"
      },
      "V41552801": {
        "v": "4708671"
      }
    },
    {
      "d": "2024-05-01",
      "V41690973": {
        "v": "161.5"
      },
      "CPI_COMMON": {
        "v": "2.4"
      },
      "CPI_MEDIAN": {
        "v": "3.2"
      },
      "CPI_TRIM": {
        "v": "3.1"
      },
      "V37151": {
        "v": "1505081"
      },
      "V37152": {
        "v": "2015914"
      },
      "V41552801": {
        "v": "4679296"
      }
    },
    {
      "d": "2024-04-01",
      "V41690973": {
        "v": "160.6"
      },
      "CPI_COMMON": {
        "v": "2.5"
      },
      "CPI_MEDIAN": {
        "v": "3.0"
      },
      "CPI_TRIM": {
        "v": "2.9"
      },
      "V37151": {
        "v": "1487597"
      },
      "V37152": {
        "v": "1990238"
      },
      "V41552801": {
        "v": "4651517"
      }
    },
    {
      "d": "2024-03-01",
      "V41690973": {
        "v": "159.8"
      },
      "CPI_COMMON": {
        "v": "2.8"
      },
      "CPI_MEDIAN": {
        "v": "3.3"
      },
      "CPI_TRIM": {
        "v": "3.2"
      },
      "V37151": {
        "v": "1469522"
      },
      "V37152": {
        "v": "1983491"
      },
      "V41552801": {
        "v": "4636718"
      }
    },
    {
      "d": "2024-02-01",
      "V41690973": {
        "v": "158.8"
      },
      "CPI_COMMON": {
        "v": "3.0"
      },
      "CPI_MEDIAN": {
        "v": "3.4"
      },
      "CPI_TRIM": {
        "v": "3.2"
      },
      "V37151": {
        "v": "1470653"
      },
      "V37152": {
        "v": "1984600"
      },
      "V41552801": {
        "v": "4625962"
      }
    },
    {
      "d": "2024-01-01",
      "V41690973": {
        "v": "158.3"
      },
      "CPI_COMMON": {
        "v": "3.3"
      },
      "CPI_MEDIAN": {
        "v": "3.7"
      },
      "CPI_TRIM": {
        "v": "3.4"
      },
      "V37151": {
        "v": "1477238"
      },
      "V37152": {
        "v": "1991145"
      },
      "V41552801": {
        "v": "4615956"
      }
    },
    {
      "d": "2023-12-01",
      "V41690973": {
        "v": "158.3"
      },
      "CPI_COMMON": {
        "v": "3.8"
      },
      "CPI_MEDIAN": {
        "v": "3.8"
      },
      "CPI_TRIM": {
        "v": "3.7"
      },
      "V37151": {
        "v": "1494258"
      },
      "V37152": {
        "v": "2009075"
      },
      "V41552801": {
        "v": "4624974"
      }
    },
    {
      "d": "2023-11-01",
      "V41690973": {
        "v": "158.8"
      },
      "CPI_COMMON": {
        "v": "3.8"
      },
      "CPI_MEDIAN": {
        "v": "3.7"
      },
      "CPI_TRIM": {
        "v": "3.5"
      },
      "V37151": {
        "v": "1513824"
      },
      "V37152": {
        "v": "2031662"
      },
      "V41552801": {
        "v": "4594862"
      }
    },
    {
      "d": "2023-10-01",
      "V41690973": {
        "v": "158.6"
      },
      "CPI_COMMON": {
        "v": "4.1"
      },
      "CPI_MEDIAN": {
        "v": "3.5"
      },
      "CPI_TRIM": {
        "v": "3.4"
      },
      "V37151": {
        "v": "1511580"
      },
      "V37152": {
        "v": "2031631"
      },
      "V41552801": {
        "v": "4579728"
      }
    },
    {
      "d": "2023-09-01",
      "V41690973": {
        "v": "158.5"
      },
      "CPI_COMMON": {
        "v": "4.3"
      },
      "CPI_MEDIAN": {
        "v": "3.8"
      },
      "CPI_TRIM": {
        "v": "3.5"
      },
      "V37151": {
        "v": "1514100"
      },
      "V37152": {
        "v": "2037915"
      },
      "V41552801": {
        "v": "4566016"
      }
    },
    {
      "d": "2023-08-01",
      "V41690973": {
        "v": "158.7"
      },
      "CPI_COMMON": {
        "v": "4.7"
      },
      "CPI_MEDIAN": {
        "v": "3.9"
      },
      "CPI_TRIM": {
        "v": "3.8"
      },
      "V37151": {
        "v": "1514824"
      },
      "V37152": {
        "v": "2040722"
      },
      "V41552801": {
        "v": "4552443"
      }
    },
    {
      "d": "2023-07-01",
      "V37151": {
        "v": "1512225"
      },
      "V37152": {
        "v": "2040540"
      },
      "V41552801": {
        "v": "4538962"
      }
    }
  ]
}